tinyshift/association_mining/__init__.py
tinyshift/association_mining/analyzer.py
tinyshift/association_mining/encoder.py
tinyshift/drift/__init__.py
tinyshift/drift/base.py
tinyshift/drift/categorical.py
tinyshift/drift/continuous.py
tinyshift/modelling/__init__.py
tinyshift/modelling/multicollinearity.py
tinyshift/modelling/residualizer.py
tinyshift/modelling/scaler.py
tinyshift/outlier/__init__.py
tinyshift/outlier/base.py
tinyshift/outlier/hbos.py
tinyshift/outlier/pca.py
tinyshift/outlier/spad.py
tinyshift/plot/__init__.py
tinyshift/plot/calibration.py
tinyshift/plot/correlation.py
tinyshift/plot/diagnostic.py
tinyshift/plot/power.py
tinyshift/series/__init__.py
tinyshift/series/forecastability.py
tinyshift/series/interpolation.py
tinyshift/series/outlier.py
tinyshift/series/stability.py
tinyshift/series/stats.py
tinyshift/stats/__init__.py
tinyshift/stats/bootstrap_bca.py
tinyshift/stats/statistical_interval.py
tinyshift/stats/utils.py
tinyshift/tests/test.pca.py
tinyshift/tests/test_hbos.py
tinyshift/tests/test_spad.py
tinyshift-1.2.3.dist-info/licenses/LICENSE
tinyshift-1.2.3.dist-info/METADATA
tinyshift-1.2.3.dist-info/WHEEL
tinyshift-1.2.3.dist-info/top_level.txt
tinyshift-1.2.3.dist-info/RECORD
