Metadata-Version: 2.4
Name: tinyshift
Version: 1.2.3
Summary: A small toolbox for mlops
Author-email: Lucas Leão <heylucasleao@gmail.com>
License-Expression: MIT
Keywords: mlops,toolbox,machine-learning
Classifier: Programming Language :: Python :: 3
Requires-Python: >=3.10
License-File: LICENSE
Requires-Dist: pandas>2.3.0
Requires-Dist: scikit-learn>1.3.0
Requires-Dist: statsmodels>=0.14.5
Provides-Extra: plot
Requires-Dist: plotly>5.22.0; extra == "plot"
Requires-Dist: kaleido<=0.2.1; extra == "plot"
Provides-Extra: notebook
Requires-Dist: nbformat>=5.10.4; extra == "notebook"
Requires-Dist: ipykernel>6.7.0; extra == "notebook"
Provides-Extra: all
Requires-Dist: plot; extra == "all"
Requires-Dist: notebook; extra == "all"
Dynamic: license-file
